odoo/addons/project_group/README.rst
odoo/addons/project_group/__init__.py
odoo/addons/project_group/__manifest__.py
odoo/addons/project_group/i18n/it.po
odoo/addons/project_group/i18n/project_group.pot
odoo/addons/project_group/models/__init__.py
odoo/addons/project_group/models/project_project.py
odoo/addons/project_group/readme/CONTRIBUTORS.md
odoo/addons/project_group/readme/DESCRIPTION.md
odoo/addons/project_group/readme/USAGE.md
odoo/addons/project_group/security/project_project.xml
odoo/addons/project_group/static/description/icon.png
odoo/addons/project_group/static/description/index.html
odoo/addons/project_group/tests/__init__.py
odoo/addons/project_group/tests/test_project_visibility.py
odoo/addons/project_group/views/project_project.xml
odoo_addon_project_group-18.0.1.0.0.3.dist-info/METADATA
odoo_addon_project_group-18.0.1.0.0.3.dist-info/WHEEL
odoo_addon_project_group-18.0.1.0.0.3.dist-info/top_level.txt
odoo_addon_project_group-18.0.1.0.0.3.dist-info/RECORD
